src/__init__.py
src/__main__.py
topsisnandinise102017121-0.0.1.dist-info/LICENSE
topsisnandinise102017121-0.0.1.dist-info/METADATA
topsisnandinise102017121-0.0.1.dist-info/WHEEL
topsisnandinise102017121-0.0.1.dist-info/entry_points.txt
topsisnandinise102017121-0.0.1.dist-info/top_level.txt
topsisnandinise102017121-0.0.1.dist-info/RECORD
