Metadata-Version: 2.1
Name: topsisnandinise102017121
Version: 0.0.1
Summary: This is a Python Package implementing TOPSIS
Home-page: https://github.com/nandinisetia/topsis
Author: Nandini Setia
Author-email: nandinisetia003@gmail.com
License: MIT
Keywords: topsis,mcda,TIET
Classifier: Development Status :: 3 - Alpha
Classifier: Intended Audience :: Developers
Classifier: Topic :: Software Development :: Build Tools
Classifier: License :: OSI Approved :: MIT License
License-File: LICENSE
Requires-Dist: numpy
Requires-Dist: pandas
